{"trial_id": "802e07dc2b8f23fdf8bc47e349f8fe87", "hyperparameters": {"space": [{"class_name": "Boolean", "config": {"name": "structured_data_block_1/normalize", "default": false, "conditions": []}}, {"class_name": "Boolean", "config": {"name": "structured_data_block_1/dense_block_1/use_batchnorm", "default": false, "conditions": []}}, {"class_name": "Choice", "config": {"name": "structured_data_block_1/dense_block_1/num_layers", "default": 2, "conditions": [], "values": [1, 2, 3], "ordered": true}}, {"class_name": "Choice", "config": {"name": "structured_data_block_1/dense_block_1/units_0", "default": 32, "conditions": [], "values": [16, 32, 64, 128, 256, 512, 1024], "ordered": true}}, {"class_name": "Choice", "config": {"name": "structured_data_block_1/dense_block_1/dropout", "default": 0.0, "conditions": [], "values": [0.0, 0.25, 0.5], "ordered": true}}, {"class_name": "Choice", "config": {"name": "structured_data_block_1/dense_block_1/units_1", "default": 32, "conditions": [], "values": [16, 32, 64, 128, 256, 512, 1024], "ordered": true}}, {"class_name": "Choice", "config": {"name": "regression_head_1/dropout", "default": 0, "conditions": [], "values": [0.0, 0.25, 0.5], "ordered": true}}, {"class_name": "Choice", "config": {"name": "optimizer", "default": "adam", "conditions": [], "values": ["adam", "sgd", "adam_weight_decay"], "ordered": false}}, {"class_name": "Choice", "config": {"name": "learning_rate", "default": 0.001, "conditions": [], "values": [0.1, 0.01, 0.001, 0.0001, 2e-05, 1e-05], "ordered": true}}], "values": {"structured_data_block_1/normalize": true, "structured_data_block_1/dense_block_1/num_layers": 2, "structured_data_block_1/dense_block_1/use_batchnorm": false, "structured_data_block_1/dense_block_1/dropout": 0, "structured_data_block_1/dense_block_1/units_0": 32, "structured_data_block_1/dense_block_1/units_1": 32, "regression_head_1/dropout": 0.0, "optimizer": "adam", "learning_rate": 0.001}}, "metrics": {"metrics": {"loss": {"direction": "min", "observations": [{"value": [0.35222917795181274], "step": 0}, {"value": [0.20217739045619965], "step": 1}, {"value": [0.18318599462509155], "step": 2}, {"value": [0.17701058089733124], "step": 3}, {"value": [0.17408931255340576], "step": 4}, {"value": [0.17254561185836792], "step": 5}, {"value": [0.17142172157764435], "step": 6}, {"value": [0.17061960697174072], "step": 7}, {"value": [0.17014950513839722], "step": 8}, {"value": [0.16959811747074127], "step": 9}, {"value": [0.1691722273826599], "step": 10}, {"value": [0.16888782382011414], "step": 11}, {"value": [0.1686844676733017], "step": 12}, {"value": [0.16852450370788574], "step": 13}, {"value": [0.16833724081516266], "step": 14}, {"value": [0.1682620793581009], "step": 15}, {"value": [0.16812478005886078], "step": 16}, {"value": [0.16803300380706787], "step": 17}, {"value": [0.16796420514583588], "step": 18}, {"value": [0.16784293949604034], "step": 19}, {"value": [0.16773159801959991], "step": 20}]}, "mean_squared_error": {"direction": "min", "observations": [{"value": [0.35222917795181274], "step": 0}, {"value": [0.20217739045619965], "step": 1}, {"value": [0.18318599462509155], "step": 2}, {"value": [0.17701058089733124], "step": 3}, {"value": [0.17408931255340576], "step": 4}, {"value": [0.17254561185836792], "step": 5}, {"value": [0.17142172157764435], "step": 6}, {"value": [0.17061960697174072], "step": 7}, {"value": [0.17014950513839722], "step": 8}, {"value": [0.16959811747074127], "step": 9}, {"value": [0.1691722273826599], "step": 10}, {"value": [0.16888782382011414], "step": 11}, {"value": [0.1686844676733017], "step": 12}, {"value": [0.16852450370788574], "step": 13}, {"value": [0.16833724081516266], "step": 14}, {"value": [0.1682620793581009], "step": 15}, {"value": [0.16812478005886078], "step": 16}, {"value": [0.16803300380706787], "step": 17}, {"value": [0.16796420514583588], "step": 18}, {"value": [0.16784293949604034], "step": 19}, {"value": [0.16773159801959991], "step": 20}]}, "val_loss": {"direction": "min", "observations": [{"value": [0.21521009504795074], "step": 0}, {"value": [0.18832571804523468], "step": 1}, {"value": [0.18150652945041656], "step": 2}, {"value": [0.1788816899061203], "step": 3}, {"value": [0.17781926691532135], "step": 4}, {"value": [0.17733889818191528], "step": 5}, {"value": [0.17693820595741272], "step": 6}, {"value": [0.1770566701889038], "step": 7}, {"value": [0.17680513858795166], "step": 8}, {"value": [0.17682813107967377], "step": 9}, {"value": [0.1766478270292282], "step": 10}, {"value": [0.17674382030963898], "step": 11}, {"value": [0.17681154608726501], "step": 12}, {"value": [0.17680801451206207], "step": 13}, {"value": [0.17684780061244965], "step": 14}, {"value": [0.176718607544899], "step": 15}, {"value": [0.17681120336055756], "step": 16}, {"value": [0.17695854604244232], "step": 17}, {"value": [0.17690064013004303], "step": 18}, {"value": [0.17698760330677032], "step": 19}, {"value": [0.1769893765449524], "step": 20}]}, "val_mean_squared_error": {"direction": "min", "observations": [{"value": [0.21521009504795074], "step": 0}, {"value": [0.18832571804523468], "step": 1}, {"value": [0.18150652945041656], "step": 2}, {"value": [0.1788816899061203], "step": 3}, {"value": [0.17781926691532135], "step": 4}, {"value": [0.17733889818191528], "step": 5}, {"value": [0.17693820595741272], "step": 6}, {"value": [0.1770566701889038], "step": 7}, {"value": [0.17680513858795166], "step": 8}, {"value": [0.17682813107967377], "step": 9}, {"value": [0.1766478270292282], "step": 10}, {"value": [0.17674382030963898], "step": 11}, {"value": [0.17681154608726501], "step": 12}, {"value": [0.17680801451206207], "step": 13}, {"value": [0.17684780061244965], "step": 14}, {"value": [0.176718607544899], "step": 15}, {"value": [0.17681120336055756], "step": 16}, {"value": [0.17695854604244232], "step": 17}, {"value": [0.17690064013004303], "step": 18}, {"value": [0.17698760330677032], "step": 19}, {"value": [0.1769893765449524], "step": 20}]}}}, "score": 0.1766478270292282, "best_step": 10, "status": "COMPLETED"}